vscode_debugger_magic/__init__.py
vscode_debugger_magic/vscode_attach.py
vscode_debugger_magic/vscode_debugger_magic.py
vscode_debugger_magic-1.3.0.dist-info/METADATA
vscode_debugger_magic-1.3.0.dist-info/WHEEL
vscode_debugger_magic-1.3.0.dist-info/top_level.txt
vscode_debugger_magic-1.3.0.dist-info/RECORD
