Metadata-Version: 2.1
Name: vscode-debugger-magic
Version: 1.3.0
Summary: A Ipython (Jupyter) magic for attaching a debugging session on VSCode 
Home-page: https://github.com/caiofcm/vscode-debugger-magic
Author: Caio Marcellos
Author-email: caiocuritiba@gmail.com
License: MIT
Platform: UNKNOWN
Classifier: License :: OSI Approved :: MIT License
Classifier: Programming Language :: Python :: 3
Classifier: Programming Language :: Python :: 3.7
Requires-Dist: ipython
Requires-Dist: ptvsd
